{
  "pages": [
    {
      "pageName": "Page4",
      "pagePath": "/drag",
      "children": [
        {
          "type": "div",
          "props": {
            "style": {
              "display": "flex",
              "justifyContent": "center",
              "alignItems": "center",
              "padding": "1em"
            }
          },
          "children": [
            {
              "type": "div",
              "children": [
                {
                  "type": "h3",
                  "props": {
                    "style": {
                      "padding": "1em",
                      "textAlign": "center"
                    }
                  },
                  "children": []
                }
              ]
            }
          ]
        },
        {
          "type": "Table",
          "variant": "default",
          "children": [],
          "namespace": "antd",
          "props": {
            "key": "5",
            "x": 17,
            "width": 1348,
            "height": 55,
            "y": 246,
            "style": {
              "width": "1348px",
              "height": "55px"
            },
            "columns": [
              {
                "className": null,
                "colSpan": null,
                "dataIndex": null,
                "title": null,
                "key": null
              },
              {
                "className": null,
                "colSpan": null,
                "dataIndex": null,
                "title": "Name",
                "key": null
              },
              {
                "className": "container",
                "colSpan": 2,
                "dataIndex": 3,
                "title": "SEX",
                "key": 5
              }
            ],
            "events": [
              "Page4_20"
            ],
            "eventsSettings": {
              "attribute": "dataSource"
            }
          }
        },
        {
          "type": "Modal",
          "variant": "default",
          "children": [
            {
              "type": "Input",
              "variant": "default",
              "children": [],
              "namespace": "antd"
            },
            {
              "type": "Select",
              "variant": "default",
              "children": [],
              "namespace": "antd",
              "props": {
                "style": {
                  "width": "200px",
                  "height": "40px"
                }
              }
            }
          ],
          "namespace": "antd",
          "props": {
            "width": 616,
            "height": 72,
            "x": 239,
            "y": 409,
            "visible": false,
            "key": "6",
            "style": {
              "border": "1px solid pink",
              "width": "616px",
              "height": "72px"
            }
          }
        },
        {
          "type": "InputGen",
          "variant": "default",
          "children": [],
          "namespace": "InputGen",
          "props": {}
        },
        {
          "type": "ModalReducer",
          "variant": "default",
          "children": [],
          "namespace": "modalReducer",
          "props": {}
        },
        {
          "type": "Input",
          "variant": "default",
          "children": [],
          "namespace": "antd",
          "props": {
            "key": "11",
            "x": 190,
            "width": 132,
            "height": 30,
            "y": 88,
            "style": {
              "width": "132px",
              "height": "30px"
            },
            "name": {
              "fieldName": "jifen",
              "fieldDesc": "积分"
            }
          }
        },
        {
          "type": "span",
          "variant": "default",
          "props": {},
          "children": [],
          "text": "您的名字"
        },
        {
          "type": "Input",
          "variant": "default",
          "children": [],
          "namespace": "antd",
          "props": {
            "key": "13",
            "x": 576,
            "width": 277,
            "height": 42,
            "y": 169,
            "style": {
              "width": "277px",
              "height": "42px"
            },
            "name": {
              "fieldName": "sex",
              "fieldDesc": "性别"
            }
          }
        },
        {
          "type": "Counter",
          "props": {},
          "children": [],
          "namespace": "antd",
          "variant": "default"
        },
        {
          "type": "Counter",
          "props": {},
          "children": [],
          "namespace": "antd",
          "variant": "default"
        },
        {
          "type": "Counter",
          "props": {},
          "children": [],
          "namespace": "antd",
          "variant": "default"
        },
        {
          "type": "Counter",
          "props": {},
          "children": [],
          "namespace": "antd",
          "variant": "default"
        },
        {
          "type": "Input",
          "variant": "default",
          "children": [],
          "namespace": "antd",
          "props": {
            "key": "18",
            "x": 425,
            "width": 100,
            "height": 50,
            "y": 81,
            "style": {
              "width": "100px",
              "height": "50px"
            },
            "name": {
              "fieldName": "school",
              "fieldDesc": "学校"
            }
          }
        },
        {
          "type": "Button",
          "variant": "default",
          "children": [],
          "namespace": "antd",
          "props": {
            "key": "14",
            "x": 1038,
            "width": 94,
            "height": 34,
            "y": 45,
            "style": {
              "width": "94px",
              "height": "34px"
            }
          }
        },
        {
          "type": "Button",
          "variant": "default",
          "children": [
            {
              "type": "span",
              "variant": "default",
              "props": {},
              "children": [],
              "text": "搜索"
            }
          ],
          "namespace": "antd",
          "props": {
            "key": "20",
            "x": 884,
            "width": 92,
            "type": "primary",
            "height": 27,
            "y": 59,
            "style": {
              "width": "92px",
              "height": "27px"
            },
            "events": [
              "Page4_20"
            ],
            "eventsSettings": {
              "eventType": "QUERY",
              "modal": "5",
              "interfaceAddress": "/push/query",
              "targetKeys": [
                {
                  "fieldName": "jifen",
                  "fieldDesc": "积分",
                  "key": "11"
                },
                {
                  "fieldName": "school",
                  "fieldDesc": "学校",
                  "key": "18"
                }
              ]
            }
          }
        }
      ]
    },
    {
      "pageName": "Page17",
      "pagePath": "/new-page",
      "children": [
        {
          "type": "div",
          "props": {
            "style": {
              "display": "flex",
              "justifyContent": "center",
              "alignItems": "center",
              "padding": "1em"
            }
          },
          "children": [
            {
              "type": "div",
              "children": [
                {
                  "type": "h3",
                  "props": {
                    "style": {
                      "padding": "1em",
                      "textAlign": "center"
                    }
                  },
                  "children": [
                    {
                      "type": "span",
                      "text": "Click on me and start creating a new cool component."
                    }
                  ]
                }
              ]
            }
          ]
        },
        {
          "type": "Input",
          "variant": "default",
          "children": [],
          "namespace": "antd",
          "props": {
            "key": "30",
            "x": 431,
            "width": 150,
            "height": 32,
            "y": 166,
            "style": {
              "width": "150px",
              "height": "32px"
            },
            "addonBefore": "http://"
          }
        },
        {
          "type": "Input",
          "variant": "default",
          "children": [],
          "namespace": "antd",
          "props": {
            "key": "31",
            "x": 355,
            "width": 88,
            "height": 30,
            "y": 46,
            "style": {
              "width": "88px",
              "height": "30px"
            }
          }
        },
        {
          "type": "Input",
          "variant": "default",
          "children": [],
          "namespace": "antd"
        },
        {
          "type": "Input",
          "variant": "default",
          "children": [],
          "namespace": "antd"
        },
        {
          "type": "Input",
          "variant": "default",
          "children": [],
          "namespace": "antd"
        },
        {
          "type": "Input",
          "variant": "default",
          "children": [],
          "namespace": "antd"
        },
        {
          "type": "Input",
          "variant": "default",
          "children": [],
          "namespace": "antd"
        },
        {
          "type": "Input",
          "variant": "default",
          "children": [],
          "namespace": "antd"
        },
        {
          "type": "Input",
          "variant": "default",
          "children": [],
          "namespace": "antd"
        },
        {
          "type": "Input",
          "variant": "default",
          "children": [],
          "namespace": "antd",
          "props": {
            "key": "35",
            "x": 47,
            "width": 100,
            "height": 50,
            "y": 147,
            "style": {
              "width": "100px",
              "height": "50px"
            }
          }
        },
        {
          "type": "Input",
          "variant": "default",
          "children": [],
          "namespace": "antd",
          "props": {
            "key": "32",
            "x": 715,
            "width": 100,
            "height": 50,
            "y": 132,
            "style": {
              "width": "100px",
              "height": "50px"
            }
          }
        },
        {
          "type": "Input",
          "variant": "default",
          "children": [],
          "namespace": "antd",
          "props": {
            "key": "34",
            "x": 226,
            "width": 100,
            "height": 50,
            "y": 214,
            "style": {
              "width": "100px",
              "height": "50px"
            },
            "defaultValue": "请输入值"
          }
        }
      ]
    },
    {
      "pageName": "Page53",
      "pagePath": "/new-page1",
      "children": []
    },
    {
      "pageName": "Page63",
      "pagePath": "/new-page2",
      "children": []
    },
    {
      "pageName": "Page72",
      "pagePath": "/new-page3",
      "children": [
        {
          "type": "div",
          "props": {
            "style": {
              "display": "flex",
              "justifyContent": "center",
              "alignItems": "center",
              "padding": "1em"
            }
          },
          "children": [
            {
              "type": "div",
              "children": [
                {
                  "type": "h3",
                  "props": {
                    "style": {
                      "padding": "1em",
                      "textAlign": "center"
                    }
                  },
                  "children": [
                    {
                      "type": "span",
                      "text": "Click on me and start creating a new cool component."
                    }
                  ]
                }
              ]
            }
          ]
        },
        {
          "type": "Input",
          "variant": "default",
          "children": [],
          "namespace": "antd"
        },
        {
          "type": "Table",
          "variant": "default",
          "children": [],
          "namespace": "antd",
          "props": {
            "key": "51",
            "x": 249,
            "width": 780,
            "height": 50,
            "y": 152,
            "style": {
              "width": "780px",
              "height": "50px"
            }
          }
        },
        {
          "type": "Input",
          "variant": "default",
          "children": [],
          "namespace": "antd",
          "props": {
            "key": "45",
            "x": 10,
            "width": 100,
            "height": 50,
            "y": 10,
            "style": {
              "width": "100px",
              "height": "50px"
            }
          }
        }
      ]
    },
    {
      "pageName": "Page54",
      "pagePath": "/new-page4",
      "children": [
        {
          "type": "div",
          "props": {
            "style": {
              "display": "flex",
              "justifyContent": "center",
              "alignItems": "center",
              "padding": "1em"
            }
          },
          "children": [
            {
              "type": "div",
              "children": [
                {
                  "type": "h3",
                  "props": {
                    "style": {
                      "padding": "1em",
                      "textAlign": "center"
                    }
                  },
                  "children": [
                    {
                      "type": "span",
                      "text": "Click on me and start creating a new cool component."
                    }
                  ]
                }
              ]
            }
          ]
        },
        {
          "type": "Select",
          "variant": "default",
          "children": [],
          "namespace": "antd",
          "props": {
            "key": "63",
            "width": 95,
            "height": 32,
            "x": 339,
            "y": 192,
            "style": {
              "width": "95px",
              "height": "32px"
            }
          }
        },
        {
          "type": "DatePicker",
          "variant": "default",
          "children": []
        }
      ]
    },
    {
      "pageName": "Page61",
      "pagePath": "/new-page5",
      "children": [
        {
          "type": "div",
          "props": {
            "style": {
              "display": "flex",
              "justifyContent": "center",
              "alignItems": "center",
              "padding": "1em"
            }
          },
          "children": [
            {
              "type": "div",
              "children": [
                {
                  "type": "h3",
                  "props": {
                    "style": {
                      "padding": "1em",
                      "textAlign": "center"
                    }
                  },
                  "children": [
                    {
                      "type": "span",
                      "text": "Click on me and start creating a new cool component."
                    }
                  ]
                }
              ]
            }
          ]
        },
        {
          "type": "Select",
          "variant": "default",
          "children": [],
          "namespace": "antd",
          "props": {
            "key": "68",
            "x": 10,
            "width": 100,
            "height": 50,
            "y": 10,
            "style": {
              "width": "100px",
              "height": "50px"
            }
          }
        }
      ]
    },
    {
      "pageName": "Page64",
      "pagePath": "/xin",
      "children": [
        {
          "type": "div",
          "props": {
            "style": {
              "display": "flex",
              "justifyContent": "center",
              "alignItems": "center",
              "padding": "1em"
            }
          },
          "children": [
            {
              "type": "div",
              "children": [
                {
                  "type": "h3",
                  "props": {
                    "style": {
                      "padding": "1em",
                      "textAlign": "center"
                    }
                  },
                  "children": [
                    {
                      "type": "span",
                      "text": "Click on me and start creating a new cool component."
                    }
                  ]
                }
              ]
            }
          ]
        },
        {
          "type": "Link",
          "props": {
            "to": "/main"
          },
          "children": [
            {
              "type": "span",
              "text": "Link to /main"
            }
          ],
          "variant": "default"
        }
      ]
    }
  ]
}
